{
  "book": "Revelation",
  "chapter": 20,
  "chapterTheme": {
    "twoWordSummary": "Millennial Reign",
    "themeWords": [
      {
        "word": "thousand",
        "strongNumber": "G5507",
        "lemma": "χίλιοι (chilioi)",
        "meaning": "a thousand"
      },
      {
        "word": "judgment",
        "strongNumber": "G2920",
        "lemma": "κρίσις (krisis)",
        "meaning": "judgment; decision; condemnation"
      }
    ]
  },
  "sentenceTheme": "Satan is bound, the saints reign with Christ for a thousand years, then final rebellion is crushed and all are judged, culminating in the second death.",
  "verses": [
    {
      "verse": 1,
      "text": "And I saw an angel come down from heaven, having the key of the bottomless pit and a great chain in his hand.",
      "highlightedWords": [
        {
          "word": "angel",
          "strongNumber": "G32",
          "lemma": "ἄγγελος (angelos)",
          "meaning": "messenger; angel"
        },
        {
          "word": "key",
          "strongNumber": "G2807",
          "lemma": "κλείς (kleis)",
          "meaning": "a key"
        }
      ]
    },
    {
      "verse": 2,
      "text": "And he laid hold on the dragon, that old serpent, which is the Devil, and Satan, and bound him a thousand years,",
      "highlightedWords": [
        {
          "word": "dragon",
          "strongNumber": "G1404",
          "lemma": "δράκων (drakōn)",
          "meaning": "dragon; serpent-like monster"
        },
        {
          "word": "Satan",
          "strongNumber": "G4567",
          "lemma": "Σατανᾶς (Satanas)",
          "meaning": "Satan; adversary"
        }
      ]
    },
    {
      "verse": 3,
      "text": "And cast him into the bottomless pit, and shut him up, and set a seal upon him, that he should deceive the nations no more, till the thousand years should be fulfilled: and after that he must be loosed a little season.",
      "highlightedWords": [
        {
          "word": "deceive",
          "strongNumber": "G4105",
          "lemma": "πλανάω (planaō)",
          "meaning": "to lead astray; deceive"
        },
        {
          "word": "nations",
          "strongNumber": "G1484",
          "lemma": "ἔθνος (ethnos)",
          "meaning": "nation; Gentiles; peoples"
        }
      ]
    },
    {
      "verse": 4,
      "text": "And I saw thrones, and they sat upon them, and judgment was given unto them: and I saw the souls of them that were beheaded for the witness of Jesus, and for the word of God, and which had not worshipped the beast, neither his image, neither had received his mark upon their foreheads, or in their hands; and they lived and reigned with Christ a thousand years.",
      "highlightedWords": [
        {
          "word": "thrones",
          "strongNumber": "G2362",
          "lemma": "θρόνος (thronos)",
          "meaning": "throne"
        },
        {
          "word": "beheaded",
          "strongNumber": "G3990",
          "lemma": "πελεκίζω (pelekizō)",
          "meaning": "to behead (with an axe)"
        }
      ]
    },
    {
      "verse": 5,
      "text": "But the rest of the dead lived not again until the thousand years were finished. This is the first resurrection.",
      "highlightedWords": [
        {
          "word": "dead",
          "strongNumber": "G3498",
          "lemma": "νεκρός (nekros)",
          "meaning": "dead; a dead person"
        },
        {
          "word": "resurrection",
          "strongNumber": "G386",
          "lemma": "ἀνάστασις (anastasis)",
          "meaning": "resurrection; rising up"
        }
      ]
    },
    {
      "verse": 6,
      "text": "Blessed and holy is he that hath part in the first resurrection: on such the second death hath no power, but they shall be priests of God and of Christ, and shall reign with him a thousand years.",
      "highlightedWords": [
        {
          "word": "second",
          "strongNumber": "G1208",
          "lemma": "δεύτερος (deuteros)",
          "meaning": "second"
        },
        {
          "word": "reign",
          "strongNumber": "G936",
          "lemma": "βασιλεύω (basileuō)",
          "meaning": "to reign; to rule as king"
        }
      ]
    },
    {
      "verse": 7,
      "text": "And when the thousand years are expired, Satan shall be loosed out of his prison,",
      "highlightedWords": [
        {
          "word": "Satan",
          "strongNumber": "G4567",
          "lemma": "Σατανᾶς (Satanas)",
          "meaning": "Satan; adversary"
        },
        {
          "word": "prison",
          "strongNumber": "G5438",
          "lemma": "φυλακή (phylakē)",
          "meaning": "prison; guard; watch"
        }
      ]
    },
    {
      "verse": 8,
      "text": "And shall go out to deceive the nations which are in the four quarters of the earth, Gog and Magog, to gather them together to battle: the number of whom is as the sand of the sea.",
      "highlightedWords": [
        {
          "word": "nations",
          "strongNumber": "G1484",
          "lemma": "ἔθνος (ethnos)",
          "meaning": "nation; Gentiles; peoples"
        },
        {
          "word": "Gog",
          "strongNumber": "G1136",
          "lemma": "Γώγ (Gōg)",
          "meaning": "Gog; prophetic enemy of God's people"
        }
      ]
    },
    {
      "verse": 9,
      "text": "And they went up on the breadth of the earth, and compassed the camp of the saints about, and the beloved city: and fire came down from God out of heaven, and devoured them.",
      "highlightedWords": [
        {
          "word": "saints",
          "strongNumber": "G40",
          "lemma": "ἅγιος (hagios)",
          "meaning": "holy one; saint"
        },
        {
          "word": "devoured",
          "strongNumber": "G2719",
          "lemma": "κατεσθίω (katesthiō)",
          "meaning": "to eat up; devour"
        }
      ]
    },
    {
      "verse": 10,
      "text": "And the devil that deceived them was cast into the lake of fire and brimstone, where the beast and the false prophet are, and shall be tormented day and night for ever and ever.",
      "highlightedWords": [
        {
          "word": "devil",
          "strongNumber": "G1228",
          "lemma": "διάβολος (diabolos)",
          "meaning": "devil; slanderer"
        },
        {
          "word": "tormented",
          "strongNumber": "G928",
          "lemma": "βασανίζω (basanizō)",
          "meaning": "to torment; torture"
        }
      ]
    },
    {
      "verse": 11,
      "text": "And I saw a great white throne, and him that sat on it, from whose face the earth and the heaven fled away; and there was found no place for them.",
      "highlightedWords": [
        {
          "word": "throne",
          "strongNumber": "G2362",
          "lemma": "θρόνος (thronos)",
          "meaning": "throne"
        },
        {
          "word": "fled",
          "strongNumber": "G5343",
          "lemma": "φεύγω (pheugō)",
          "meaning": "to flee; run away"
        }
      ]
    },
    {
      "verse": 12,
      "text": "And I saw the dead, small and great, stand before God; and the books were opened: and another book was opened, which is the book of life: and the dead were judged out of those things which were written in the books, according to their works.",
      "highlightedWords": [
        {
          "word": "books",
          "strongNumber": "G975",
          "lemma": "βιβλίον (biblion)",
          "meaning": "book; scroll"
        },
        {
          "word": "judged",
          "strongNumber": "G2919",
          "lemma": "κρίνω (krinō)",
          "meaning": "to judge; decide"
        }
      ]
    },
    {
      "verse": 13,
      "text": "And the sea gave up the dead which were in it; and death and hell delivered up the dead which were in them: and they were judged every man according to their works.",
      "highlightedWords": [
        {
          "word": "sea",
          "strongNumber": "G2281",
          "lemma": "θάλασσα (thalassa)",
          "meaning": "sea"
        },
        {
          "word": "hell",
          "strongNumber": "G86",
          "lemma": "ᾅδης (hadēs)",
          "meaning": "Hades; the realm of the dead"
        }
      ]
    },
    {
      "verse": 14,
      "text": "And death and hell were cast into the lake of fire. This is the second death.",
      "highlightedWords": [
        {
          "word": "death",
          "strongNumber": "G2288",
          "lemma": "θάνατος (thanatos)",
          "meaning": "death"
        },
        {
          "word": "lake",
          "strongNumber": "G3041",
          "lemma": "λίμνη (limnē)",
          "meaning": "lake; pool"
        }
      ]
    },
    {
      "verse": 15,
      "text": "And whosoever was not found written in the book of life was cast into the lake of fire.",
      "highlightedWords": [
        {
          "word": "book",
          "strongNumber": "G975",
          "lemma": "βιβλίον (biblion)",
          "meaning": "book; scroll"
        },
        {
          "word": "fire",
          "strongNumber": "G4442",
          "lemma": "πῦρ (pyr)",
          "meaning": "fire"
        }
      ]
    }
  ]
}