{
  "book": "Revelation",
  "chapter": 7,
  "chapterTheme": {
    "twoWordSummary": "Sealed Multitude",
    "themeWords": [
      {
        "word": "sealed",
        "strongNumber": "G4972",
        "lemma": "sphragizō",
        "meaning": "to seal, mark with a seal, secure as owned"
      },
      {
        "word": "Lamb",
        "strongNumber": "G721",
        "lemma": "arnion",
        "meaning": "a lamb; figuratively, Christ"
      }
    ]
  },
  "sentenceTheme": "God restrains judgment, seals 144,000 from Israel, and a great multitude from all nations worship before the throne and the Lamb.",
  "verses": [
    {
      "verse": 1,
      "text": "And after these things I saw four angels standing on the four corners of the earth, holding the four winds of the earth, that the wind should not blow on the earth, nor on the sea, nor on any tree.",
      "highlightedWords": [
        {
          "word": "angels",
          "strongNumber": "G32",
          "lemma": "angelos",
          "meaning": "a messenger, angel"
        },
        {
          "word": "earth",
          "strongNumber": "G1093",
          "lemma": "gē",
          "meaning": "earth, land, soil"
        }
      ]
    },
    {
      "verse": 2,
      "text": "And I saw another angel ascending from the east, having the seal of the living God: and he cried with a loud voice to the four angels, to whom it was given to hurt the earth and the sea,",
      "highlightedWords": [
        {
          "word": "seal",
          "strongNumber": "G4973",
          "lemma": "sphragis",
          "meaning": "a seal, signet"
        },
        {
          "word": "God",
          "strongNumber": "G2316",
          "lemma": "theos",
          "meaning": "God, the supreme Deity"
        }
      ]
    },
    {
      "verse": 3,
      "text": "Saying, Hurt not the earth, neither the sea, nor the trees, till we have sealed the servants of our God in their foreheads.",
      "highlightedWords": [
        {
          "word": "sealed",
          "strongNumber": "G4972",
          "lemma": "sphragizō",
          "meaning": "to seal, mark with a seal, secure as owned"
        },
        {
          "word": "servants",
          "strongNumber": "G1401",
          "lemma": "doulos",
          "meaning": "a slave, servant, bondservant"
        }
      ]
    },
    {
      "verse": 4,
      "text": "And I heard the number of them which were sealed: and there were sealed an hundred and forty and four thousand of all the tribes of the children of Israel.",
      "highlightedWords": [
        {
          "word": "number",
          "strongNumber": "G706",
          "lemma": "arithmos",
          "meaning": "a number, total"
        },
        {
          "word": "Israel",
          "strongNumber": "G2474",
          "lemma": "Israēl",
          "meaning": "Israel; the Jewish people"
        }
      ]
    },
    {
      "verse": 5,
      "text": "Of the tribe of Juda were sealed twelve thousand. Of the tribe of Reuben were sealed twelve thousand. Of the tribe of Gad were sealed twelve thousand.",
      "highlightedWords": [
        {
          "word": "tribe",
          "strongNumber": "G5443",
          "lemma": "phylē",
          "meaning": "a tribe, clan, lineage"
        },
        {
          "word": "thousand",
          "strongNumber": "G5505",
          "lemma": "chilioi",
          "meaning": "a thousand"
        }
      ]
    },
    {
      "verse": 6,
      "text": "Of the tribe of Aser were sealed twelve thousand. Of the tribe of Nephthalim were sealed twelve thousand. Of the tribe of Manasses were sealed twelve thousand.",
      "highlightedWords": [
        {
          "word": "tribe",
          "strongNumber": "G5443",
          "lemma": "phylē",
          "meaning": "a tribe, clan, lineage"
        },
        {
          "word": "thousand",
          "strongNumber": "G5505",
          "lemma": "chilioi",
          "meaning": "a thousand"
        }
      ]
    },
    {
      "verse": 7,
      "text": "Of the tribe of Simeon were sealed twelve thousand. Of the tribe of Levi were sealed twelve thousand. Of the tribe of Issachar were sealed twelve thousand.",
      "highlightedWords": [
        {
          "word": "tribe",
          "strongNumber": "G5443",
          "lemma": "phylē",
          "meaning": "a tribe, clan, lineage"
        },
        {
          "word": "thousand",
          "strongNumber": "G5505",
          "lemma": "chilioi",
          "meaning": "a thousand"
        }
      ]
    },
    {
      "verse": 8,
      "text": "Of the tribe of Zabulon were sealed twelve thousand. Of the tribe of Joseph were sealed twelve thousand. Of the tribe of Benjamin were sealed twelve thousand.",
      "highlightedWords": [
        {
          "word": "tribe",
          "strongNumber": "G5443",
          "lemma": "phylē",
          "meaning": "a tribe, clan, lineage"
        },
        {
          "word": "thousand",
          "strongNumber": "G5505",
          "lemma": "chilioi",
          "meaning": "a thousand"
        }
      ]
    },
    {
      "verse": 9,
      "text": "After this I beheld, and, lo, a great multitude, which no man could number, of all nations, and kindreds, and people, and tongues, stood before the throne, and before the Lamb, clothed with white robes, and palms in their hands;",
      "highlightedWords": [
        {
          "word": "multitude",
          "strongNumber": "G3793",
          "lemma": "ochlos",
          "meaning": "a crowd, multitude"
        },
        {
          "word": "throne",
          "strongNumber": "G2362",
          "lemma": "thronos",
          "meaning": "a throne, seat of authority"
        }
      ]
    },
    {
      "verse": 10,
      "text": "And cried with a loud voice, saying, Salvation to our God which sitteth upon the throne, and unto the Lamb.",
      "highlightedWords": [
        {
          "word": "Salvation",
          "strongNumber": "G4991",
          "lemma": "sōtēria",
          "meaning": "salvation, deliverance"
        },
        {
          "word": "Lamb",
          "strongNumber": "G721",
          "lemma": "arnion",
          "meaning": "a lamb; figuratively, Christ"
        }
      ]
    },
    {
      "verse": 11,
      "text": "And all the angels stood round about the throne, and about the elders and the four beasts, and fell before the throne on their faces, and worshipped God,",
      "highlightedWords": [
        {
          "word": "elders",
          "strongNumber": "G4245",
          "lemma": "presbyteros",
          "meaning": "an elder, older one; a council member"
        },
        {
          "word": "beasts",
          "strongNumber": "G2226",
          "lemma": "zōon",
          "meaning": "a living creature"
        }
      ]
    },
    {
      "verse": 12,
      "text": "Saying, Amen: Blessing, and glory, and wisdom, and thanksgiving, and honour, and power, and might, be unto our God for ever and ever. Amen.",
      "highlightedWords": [
        {
          "word": "Amen",
          "strongNumber": "G281",
          "lemma": "amēn",
          "meaning": "truly, so be it"
        },
        {
          "word": "glory",
          "strongNumber": "G1391",
          "lemma": "doxa",
          "meaning": "glory, honor, splendor"
        }
      ]
    },
    {
      "verse": 13,
      "text": "And one of the elders answered, saying unto me, What are these which are arrayed in white robes? and whence came they?",
      "highlightedWords": [
        {
          "word": "elders",
          "strongNumber": "G4245",
          "lemma": "presbyteros",
          "meaning": "an elder, older one; a council member"
        },
        {
          "word": "robes",
          "strongNumber": "G4749",
          "lemma": "stolē",
          "meaning": "a long robe, stately garment"
        }
      ]
    },
    {
      "verse": 14,
      "text": "And I said unto him, Sir, thou knowest. And he said to me, These are they which came out of great tribulation, and have washed their robes, and made them white in the blood of the Lamb.",
      "highlightedWords": [
        {
          "word": "tribulation",
          "strongNumber": "G2347",
          "lemma": "thlipsis",
          "meaning": "affliction, tribulation, pressure"
        },
        {
          "word": "blood",
          "strongNumber": "G129",
          "lemma": "haima",
          "meaning": "blood"
        }
      ]
    },
    {
      "verse": 15,
      "text": "Therefore are they before the throne of God, and serve him day and night in his temple: and he that sitteth on the throne shall dwell among them.",
      "highlightedWords": [
        {
          "word": "temple",
          "strongNumber": "G3485",
          "lemma": "naos",
          "meaning": "temple, inner sanctuary"
        },
        {
          "word": "dwell",
          "strongNumber": "G4637",
          "lemma": "skēnoō",
          "meaning": "to dwell, to tabernacle"
        }
      ]
    },
    {
      "verse": 16,
      "text": "They shall hunger no more, neither thirst any more; neither shall the sun light on them, nor any heat.",
      "highlightedWords": [
        {
          "word": "hunger",
          "strongNumber": "G3983",
          "lemma": "peinaō",
          "meaning": "to hunger, be hungry"
        },
        {
          "word": "thirst",
          "strongNumber": "G1372",
          "lemma": "dipsaō",
          "meaning": "to thirst"
        }
      ]
    },
    {
      "verse": 17,
      "text": "For the Lamb which is in the midst of the throne shall feed them, and shall lead them unto living fountains of waters: and God shall wipe away all tears from their eyes.",
      "highlightedWords": [
        {
          "word": "Lamb",
          "strongNumber": "G721",
          "lemma": "arnion",
          "meaning": "a lamb; figuratively, Christ"
        },
        {
          "word": "fountains",
          "strongNumber": "G4077",
          "lemma": "pēgē",
          "meaning": "a spring, fountain, well"
        }
      ]
    }
  ]
}